{
  "items": [
    {
      "id": "0c10a1741398",
      "topic": "Janella Hernandez Explores Mexican Pride, Community and Soccer Fandom at the LA FIFA Fan Festival",
      "traffic": "",
      "detected_at": "2026-06-22T22:44:00.609293+00:00",
      "search_url": "https://hypebeast.com/2026/6/janella-hernandez-doordash-la-fan-festival-interviews",
      "source_name": "Hypebeast",
      "source_type": "feed",
      "haiku_score": 8
    },
    {
      "id": "52e0803ce68e",
      "topic": "11 Artists Reimagine the Humble Football for IMAZ Benefit Auction",
      "traffic": "",
      "detected_at": "2026-06-22T22:44:00.609293+00:00",
      "search_url": "https://hypebeast.com/2026/6/imaz-foundation-chapter-one-football-exhibition-nyc",
      "source_name": "Hypebeast",
      "source_type": "feed",
      "haiku_score": 8
    },
    {
      "id": "6bef3ba2efbe",
      "topic": "The Nike Sabrina 4 Pours Out A High-Energy Red Colorway",
      "traffic": "",
      "detected_at": "2026-06-22T22:44:00.609293+00:00",
      "search_url": "https://sneakernews.com/2026/06/22/nike-sabrina-4-red-black/",
      "source_name": "Sneaker News",
      "source_type": "feed",
      "haiku_score": 8,
      "cluster_id": "7ea48afeaca7d569"
    },
    {
      "id": "b6313f7b71f9",
      "topic": "First Look At The Nike A’Two “MVP”",
      "traffic": "",
      "detected_at": "2026-06-22T22:44:00.609293+00:00",
      "search_url": "https://sneakernews.com/2026/06/22/nike-a-two-mvp-pink-green/",
      "source_name": "Sneaker News",
      "source_type": "feed",
      "haiku_score": 8,
      "cluster_id": "d11bfa37bb6fde09"
    },
    {
      "id": "163cec32f21f",
      "topic": "Tom Hanks Says Disney Could Use AI to Recreate Woody’s Voice for ‘Toy Story 6’ and Beyond If He Doesn’t Return: ‘It’s a Scary Thought’",
      "traffic": "",
      "detected_at": "2026-06-22T22:44:00.609293+00:00",
      "search_url": "https://variety.com/2026/film/news/tom-hanks-ai-woody-voice-toy-story-6-1236787237/",
      "source_name": "Variety",
      "source_type": "feed",
      "haiku_score": 8
    },
    {
      "id": "26af3dba1af0",
      "topic": "Eamon Farren, Arlo Green, Miranda Otto and Sacha Horler Join Hugo Weaving in Australian Legal Drama ‘The Great White’ From ‘Slow Horses’ Banner See-Saw (EXCLUSIVE)",
      "traffic": "",
      "detected_at": "2026-06-22T22:44:00.609293+00:00",
      "search_url": "https://variety.com/2026/tv/global/see-saw-australian-legal-drama-the-great-white-filming-1236787149/",
      "source_name": "Variety",
      "source_type": "feed",
      "haiku_score": 8
    },
    {
      "id": "4dc409582da8",
      "topic": "Second Note Sent to Media Said Nancy Guthrie Was Dead",
      "traffic": "",
      "detected_at": "2026-06-22T22:44:00.609293+00:00",
      "search_url": "https://variety.com/2026/tv/news/second-note-nancy-guthrie-dead-savannah-guthrie-1236787674/",
      "source_name": "Variety",
      "source_type": "feed",
      "haiku_score": 8
    },
    {
      "id": "c99a076d5ae7",
      "topic": "Tom Holland Told Zendaya ‘Right Away’ That ‘Robert Downey Jr. Is Coming Back’ to Marvel After Finding Out Early About ‘Avengers: Doomsday’",
      "traffic": "",
      "detected_at": "2026-06-22T22:44:00.609293+00:00",
      "search_url": "https://variety.com/2026/film/news/tom-holland-zendaya-robert-downey-jr-avengers-doomsday-1236787160/",
      "source_name": "Variety",
      "source_type": "feed",
      "haiku_score": 8
    },
    {
      "id": "895a664657b0",
      "topic": "A Source of Mysterious Repeating Radio Signals From Space Has Been Identified",
      "traffic": "",
      "detected_at": "2026-06-22T22:44:00.609293+00:00",
      "search_url": "https://www.wired.com/story/a-source-of-mysterious-repeating-radio-signals-from-space-has-been-identified/",
      "source_name": "WIRED",
      "source_type": "feed",
      "haiku_score": 8
    },
    {
      "id": "31a9f69039ff",
      "topic": "Shareholders sue Uber’s board over sexual assaults, other incidents",
      "traffic": "",
      "detected_at": "2026-06-22T22:44:00.609293+00:00",
      "search_url": "https://techcrunch.com/2026/06/22/shareholders-sue-ubers-board-over-sexual-assaults-other-incidents/",
      "source_name": "TechCrunch",
      "source_type": "feed",
      "haiku_score": 8
    },
    {
      "id": "425460de6b08",
      "topic": "Meta is 'pausing' employee tracking program after it let the whole company see sensitive data",
      "traffic": "",
      "detected_at": "2026-06-22T22:44:00.609293+00:00",
      "search_url": "https://www.engadget.com/2199458/meta-is-pausing-employee-tracking-program-after-it-let-the-whole-company-see-sensitive-data/",
      "source_name": "Engadget",
      "source_type": "feed",
      "haiku_score": 8
    },
    {
      "id": "5fbd5a5fa36c",
      "topic": "GM installs robots at flagship EV factory after laying off 1,300 workers",
      "traffic": "",
      "detected_at": "2026-06-22T22:44:00.609293+00:00",
      "search_url": "https://arstechnica.com/ai/2026/06/gm-installs-robots-at-flagship-ev-factory-after-laying-off-1300-workers/",
      "source_name": "Ars Technica",
      "source_type": "feed",
      "haiku_score": 8
    },
    {
      "id": "4d44a290c6ad",
      "topic": "Report: Kennedy Space Center not ready for era of super heavy rockets",
      "traffic": "",
      "detected_at": "2026-06-22T22:44:00.609293+00:00",
      "search_url": "https://arstechnica.com/space/2026/06/report-kennedy-space-center-not-ready-for-era-of-super-heavy-rockets/",
      "source_name": "Ars Technica",
      "source_type": "feed",
      "haiku_score": 8
    },
    {
      "id": "8053362ab5a0",
      "topic": "'We'll see' — Trump hedges on guarantee Iran won't use oil profits to rebuild military",
      "traffic": "",
      "detected_at": "2026-06-22T22:44:00.609293+00:00",
      "search_url": "https://www.cnbc.com/2026/06/22/trump-iran-war-oil-profits-rebuild-military.html",
      "source_name": "CNBC",
      "source_type": "feed",
      "haiku_score": 8
    },
    {
      "id": "8a8437ff32ea",
      "topic": "Tesla faces federal probe after Model 3 slams into Texas home, killing 76-year-old",
      "traffic": "",
      "detected_at": "2026-06-22T22:44:00.609293+00:00",
      "search_url": "https://www.cnbc.com/2026/06/22/tesla-nhtsa-model-3-crash-autopilot-katy-texas.html",
      "source_name": "CNBC",
      "source_type": "feed",
      "haiku_score": 8
    },
    {
      "id": "1b91568f4fb8",
      "topic": "Trump Administration Executive Order Places Quantum at Center of Federal Technology Strategy - The Quantum Insider",
      "traffic": "",
      "detected_at": "2026-06-22T22:44:00.609293+00:00",
      "search_url": "https://news.google.com/rss/articles/CBMizwFBVV95cUxOWEhqWV90MktsUUJPdjMwMmsyX1dHbEs5eXN5NlkwdDZrY0hEWmVnb0NLMlY2RTF5cDMxUmNUNGRTenVvcFkxQ29ucXIwUVJiZ01oVzlhc2gtNlJ4bUhTZVF3c2pCX2hNMkthNF92a3pOQjIxeUhrc0tmUGR4c3haWXN4QUpzQjFJUnBHVjAtWHFaTVBmcGFqbjhtNG80d1pzcXA1anowRkdJcHVQNlBNVTV0Qk9wanFUSVZlZnFaaDZqVkY2UmlnUE1OTktVV0k?oc=5",
      "source_name": "Google News - Technology",
      "source_type": "feed",
      "haiku_score": 8
    },
    {
      "id": "a407582c6dbc",
      "topic": "JMIR Publications and Eindhoven University of Technology Announce Two-Year Extension of Unlimited Open Access Publishing Agreement - Journal of Medical Internet Research (JMIR)",
      "traffic": "",
      "detected_at": "2026-06-22T22:44:00.609293+00:00",
      "search_url": "https://news.google.com/rss/articles/CBMiT0FVX3lxTE8zWlgwbldsUGVyZER1MDBJRkV5ZkplR3g2TWVMczNVdTNIUmRGOGY3SVpWbTBNQkExV3MxNEIwRzN4S3J0cFZfZHRqdW51SVE?oc=5",
      "source_name": "Google News - Technology",
      "source_type": "feed",
      "haiku_score": 8
    },
    {
      "id": "6d0c013ec4ca",
      "topic": "ODU’s new institute to strengthen national security through research, technology solutions, leaders say - WHRO",
      "traffic": "",
      "detected_at": "2026-06-22T22:44:00.609293+00:00",
      "search_url": "https://news.google.com/rss/articles/CBMi4AFBVV95cUxPU3VQNkFQZTBWcDgta0Zpd1hKZmtHMVo2ZERVcHIzbnYtQzBRc2JDRWN0M3JBYTNZbVdVT3YyLURKZkRBUFFfVUVYQnRaQTRqem4zR3hHU3Q1OHNrMTFyR3V1WnplcUpNRi1zemgzT25hcVlWdzVMZHVsOVotbk43MTU1NmVzN2w0SHN4ckFEbzhxQ2V5ZUMwQTJuOVp6YzkyR3NoM05TdmxNRlgtamNYcmpxZ3VLV1huYWM3Z0E2NDNmVmFJSUNmUXVaTm1WUXVBUGZ0aUZoZUEwU2ZHZjh4dQ?oc=5",
      "source_name": "Google News - Technology",
      "source_type": "feed",
      "haiku_score": 8
    },
    {
      "id": "62b448871723",
      "topic": "Column: For rural Virginia, data centers are more than technology - The Virginian-Pilot",
      "traffic": "",
      "detected_at": "2026-06-22T22:44:00.609293+00:00",
      "search_url": "https://news.google.com/rss/articles/CBMipgFBVV95cUxQa0gzSkxMcVM3QXlobk9oeFJ1VE5lMmFCV0x5UGZEaFVSOXBjdXY5V05jU0F4eHZKQ1V3MUNKV1Nhb0dzR1JvMHJ5akNwUURuWlI4eEQySzI5LW1ZdWVWZkdwMVYzd3lQUmc4UWNzTmV0TmJQeFZyNFpWcHgzTml0bXR6RXp6OFVFaWkxcTdlX2E5aDBoTzBhZWhqZ1dyOHh2Q05RX0ZR?oc=5",
      "source_name": "Google News - Technology",
      "source_type": "feed",
      "haiku_score": 8
    },
    {
      "id": "d28aa6215719",
      "topic": "AI Shifts Cybersecurity Focus from Finding Flaws to Fixing Them - Campus Technology",
      "traffic": "",
      "detected_at": "2026-06-22T22:44:00.609293+00:00",
      "search_url": "https://news.google.com/rss/articles/CBMiywFBVV95cUxOd0RzS01nUHc0dEhEME1YTWliWFphYl9ZSWFoVTZ4Uk9sS1NaSnAyZlY4dzhtWEhSYVdpZkV5UDhJUFpLelJqbTFDRnBTZWh2LTJSYWZPaExORWxKNnBZN1l5OTdCdjI2RmEzVWdwaXcweE5FTkMxenY3dTRZQmQyckVuSl9BNC1iWTljaUtJOU9WMk1ZeTluazFVanFsTzhnVW9hZFk3cUJacFhvM0FTX2NybUhJeS1SOXBITkc4Y2xzYTgyNVZYNGVDUQ?oc=5",
      "source_name": "Google News - Technology",
      "source_type": "feed",
      "haiku_score": 8
    },
    {
      "id": "5dec1839ce92",
      "topic": "The Surprise Star of the World Cup? Haaland’s Birkin Collection - Highsnobiety",
      "traffic": "",
      "detected_at": "2026-06-22T22:44:00.609293+00:00",
      "search_url": "https://news.google.com/rss/articles/CBMiZ0FVX3lxTE9WVjc4bHNQRVhUVDFkNGNRM0E2TXdQaXZxd3R4VmZ4aGZuNlBTZkpzb0RIaHJOV1doaWdpX1NZQ2UxSTY2TWwzUVNYSmFrVWNOMnIxNUhtU2NZemdQY3NzU3lQaUJ3LUE?oc=5",
      "source_name": "Highsnobiety",
      "source_type": "feed",
      "haiku_score": 8
    },
    {
      "id": "d5a52a13a505",
      "topic": "NBA mock draft, live news, rumors: What we're hearing one day before event - USA Today",
      "traffic": "",
      "detected_at": "2026-06-22T22:44:00.609293+00:00",
      "search_url": "https://news.google.com/rss/articles/CBMiwwFBVV95cUxQRmhLVktKWm9tSlhDa1hPUUgwdVFxSHZhQ2tFdjdUb1psZHJaLUpzUU5tZVRZZEhhNDQxM1JFelBQcm9LRzB6RTNfc1ZjMlkxRGh1bGtGRk5WNVZuMW5yTGJQdzlWeWJyV0xpdkFJT3lkZmFPRzlrd0w4WEEycGVmVkgyT01MVDVUTEU5WEF6MXVldWU3TW9DWnZ2cndSMWNWcnZHc1Rid0dERDdrRU10bEdyMG8wNHNzMVpidVozaFI0eGM?oc=5",
      "source_name": "Google News - NBA",
      "source_type": "feed",
      "haiku_score": 8
    },
    {
      "id": "d46bfd3d4b5e",
      "topic": "‘Absolutely jaw-dropping deal’: NBA world shocked by Trae Young contract - Yahoo Sports",
      "traffic": "",
      "detected_at": "2026-06-22T22:44:00.609293+00:00",
      "search_url": "https://news.google.com/rss/articles/CBMiiAFBVV95cUxQSDJ4NG03b0FLTjNqV0FCMjN5MEpwUkQxSkhHXzRnWERVNzJMU21lUkFiZXgxZnpWSVFBTkpHZC1wSnc3dG1hSzJHR29uczBhY1BuZ3FXTDl1bnUyUlo5S2luZDVjUGc1OWRVS1I2U3dTTzVha2NYbFVjX3dFY3BEbnRMelJ2aVZR?oc=5",
      "source_name": "Google News - NBA",
      "source_type": "feed",
      "haiku_score": 8
    },
    {
      "id": "5183a236cebb",
      "topic": "Dusty May’s move to the NBA shocked college hoops, but there were signs it shouldn’t have - The New York Times",
      "traffic": "",
      "detected_at": "2026-06-22T22:44:00.609293+00:00",
      "search_url": "https://news.google.com/rss/articles/CBMimwFBVV95cUxPb3ZaLTFLVjRaU0w2bnloNEJ6WnRzd0doWUxyYzUwMzdLLVRUQXhTaUprMzBvaEdBcjdndEJpX0FsYXI1Y3poM0hGUlM5OWoyaFAxSTNJUzNIeXNieTMxVVJueGlIV003empuVGRzalIyYldFZXJ6amZLT1lINllvQjFBNkNxdXdPZU5WUXJIdVB1b1R2ZXdwX21WUQ?oc=5",
      "source_name": "Google News - NBA",
      "source_type": "feed",
      "haiku_score": 8,
      "cluster_id": "2e1894a581f9deba"
    },
    {
      "id": "28fd6b799fe2",
      "topic": "2026 NBA Draft Scouting Report for Ryan Conwell - Bleacher Report",
      "traffic": "",
      "detected_at": "2026-06-22T22:44:00.609293+00:00",
      "search_url": "https://news.google.com/rss/articles/CBMikgFBVV95cUxNRElnNDRwaC1MTFQ4alRNbkdmVmlJalpaellPOFVKUjFVUXhZY2xrdEUtLXo1QVNjWTRBUU1TVjBYbkJSYzBHdzhuRWtqVUtKMmp3ZGVfdUdNX212Zjk2VU0xUFBaNk1zaFdiZWJSdFFYWjNUY2hSemtRUS02V0EtSjBUTUhRVUtUOC1BRzlCQ0JKdw?oc=5",
      "source_name": "Google News - NBA",
      "source_type": "feed",
      "haiku_score": 8
    },
    {
      "id": "9c58ed22afc9",
      "topic": "Timberwolves NBA Draft Preview: Picks, Prospects to Know, How to Watch - Sports Illustrated",
      "traffic": "",
      "detected_at": "2026-06-22T22:44:00.609293+00:00",
      "search_url": "https://news.google.com/rss/articles/CBMiqAFBVV95cUxObXpHa0NPbXNUSkFYSFlSUFFYaVIxV2FUQW5Sd2NTeWZHQllNWEdQX1Z1UkpFSzM3RzdZQ3JERlo4M2xrR2tYQUM2Q2NJZTNtQXFQLVVtNlNVbzVZRHJVbzRCSEJhOXdyQ0FFR2RBMnB3TnBmbGZadkxKV1VYNU5fTXAzWGxIaWlVWkcxRW5VV21BT3FTazVYTzVTbHh6VjUwUHZwS2ZUX1Y?oc=5",
      "source_name": "Google News - NBA",
      "source_type": "feed",
      "haiku_score": 8
    },
    {
      "id": "c31700f966ba",
      "topic": "Memory's price surge threatens Apple's 'magic formula' — and the economy: WSJ reporter - Yahoo Finance",
      "traffic": "",
      "detected_at": "2026-06-22T22:44:00.609293+00:00",
      "search_url": "https://news.google.com/rss/articles/CBMixgFBVV95cUxOQS1sVEkzc3ZELTE4ZFVaOVdzRFVFMjlyMkRJU0xoc2FvV3MxY1RpMXljWlZDTlcxQXR5SFkwSjNnRjUtcVNGdDIzT0xGVG9fT2t4dFpCUTh0dzJURldCX19yem5mT0tMNGZzS21ySzV3aDR6SU5YYnZjbHhvMlBmaWR2bnd6YndpY2pOY0lLem5LbmkzMEh3Y3c0cWNPMmkyZTRveEEyZlN0SHB2X1NHekpidk5ucnVmd3JqaHgzU2hUSjdxNVE?oc=5",
      "source_name": "Yahoo Finance",
      "source_type": "feed",
      "haiku_score": 8
    },
    {
      "id": "0aa824ba5232",
      "topic": "University of Colorado purchases high-rise in Denver's Central Business District - CBS News",
      "traffic": "",
      "detected_at": "2026-06-22T22:44:00.609293+00:00",
      "search_url": "https://news.google.com/rss/articles/CBMiugFBVV95cUxNdVVlZzBFSDFTRHNLVm9YZHlYZlVhSlJ1c2h0QU9hWjJQckJTeWFrbkxkeVZTS20xTEFMaXRJVGIwWWRKd2pnQ2Rsb2hsTk05UUtvNC05YVNta1ZDZ0x0d1RnY3I4cURKXzJGS2YwVWJqT21mVUo1b2lQOWJzYWY2QnNDU2NrWTJzLXZjOXR4bzFLSlhLWWFaOUxhX2s3cDBYSXZXWWdWd2xFOUtLcE90aTFhNmh5OGtvamc?oc=5",
      "source_name": "Google News - Business",
      "source_type": "feed",
      "haiku_score": 8
    },
    {
      "id": "c69d136054f8",
      "topic": "Sacramento business groups form coalition to fight for reforms at City Hall - Sacramento Bee",
      "traffic": "",
      "detected_at": "2026-06-22T22:44:00.609293+00:00",
      "search_url": "https://news.google.com/rss/articles/CBMiakFVX3lxTE9hOFdoSy1tLVNUN1NZek95TWVvbXMwUFUxeS1CNXdaNEFnTHFvOF9BcjByZ28ydjNtcjBfX1dmN1VWQmpQNkh1OU15OWlPV2RuOEgyR3QwamJBNDBTT2NQeTgwR3VzUk9SSXfSAWpBVV95cUxNSm9VVHZsaEZCQTJLMEJsYmNYMjJSaF8zYTduYVZ0N2xMcm5xeGpySEJNdzBtY1dVN1JLdU9jZXZVTTRGVG9qRk9NSzNiYmlvZEFjTU1RRTNvSGlWNUR0bjBZcGc0Z1BtdVhn?oc=5",
      "source_name": "Google News - Business",
      "source_type": "feed",
      "haiku_score": 8
    },
    {
      "id": "6831bb3bec77",
      "topic": "What 70 Years In Business Has Taught Us About Leadership - Forbes",
      "traffic": "",
      "detected_at": "2026-06-22T22:44:00.609293+00:00",
      "search_url": "https://news.google.com/rss/articles/CBMitAFBVV95cUxNY3VRYTVRVE1lZlM3YjZJOGxRWU0tbEx4MlJ4eU03UHZMam5uYjczcWRzSUlDbElEM1FwWnB1ckhtN3g0aFI2VkFwV05zMUdxeE9GWW9LVlZKZi00TkFlV3JYcnJRSmE5aFpnQzgwbG1PNnZFZ1ktTGZGcEg5T3J4WVR5VGJhWmxGOTFWT3RkbGFBdWdXcGdCdGROaUJCMWNXOHhMdXk0aWtUVXR3YWFrYUtScmY?oc=5",
      "source_name": "Google News - Business",
      "source_type": "feed",
      "haiku_score": 8
    },
    {
      "id": "34b6bba1f235",
      "topic": "CMU Davis School of Business Hosts Rural Entrepreneurship Symposium - Colorado Mesa University",
      "traffic": "",
      "detected_at": "2026-06-22T22:44:00.609293+00:00",
      "search_url": "https://news.google.com/rss/articles/CBMitgFBVV95cUxObnZYV3Nla3hRZGJJQTlkaXFFTExMU2p3ZzAtdnVrc3R1aElnaUtfVFRiVDBHcklqV0g4NTVtRlVyWEszQkgtRmtRMGVmV09oOFFPNkZGSlRpRGhNUWk0OHhVRWw1QkpFLWpnczVGUUpKdEQ1M1p6WkZ3YktPZHdXQ0c1bFpRYld0aDRqVTBmaXBSZWFVX3BKWDBnamlQT2w0MWk1S2RZV1BFWkZBNUNYcG1EaHZIQQ?oc=5",
      "source_name": "Google News - Business",
      "source_type": "feed",
      "haiku_score": 8
    },
    {
      "id": "737343e0d39b",
      "topic": "Fernando Mendoza embraces business of being a franchise quarterback | Raiders News | Sports - Las Vegas Review-Journal",
      "traffic": "",
      "detected_at": "2026-06-22T22:44:00.609293+00:00",
      "search_url": "https://news.google.com/rss/articles/CBMivgFBVV95cUxQUjhQMXY2R29GYmJyNlVvTWp6R0ZvamMxMmlMcHBJYy1fYnl3Mm51aXJxdG9hVWowZ194MUtqa3NNMHp4MWFmN01HZjBNT0lxNmk0TDAzdkJITXZab2diUnJfNkxNbUFfYkVERnlfRndCdFFEM2phVTN6TlBUUWF3VkV1QklLXzRWVXBaTW1aMWltMG1oS1RndEFFc2QwZ05vRXRsTTJOeng3N1VqRXdxdUVUQnRMa1dxZ0lnTTV3?oc=5",
      "source_name": "Google News - Business",
      "source_type": "feed",
      "haiku_score": 8
    },
    {
      "id": "4ca6ca7580f3",
      "topic": "AI Personal Finance - FOX 13 Tampa Bay",
      "traffic": "",
      "detected_at": "2026-06-22T22:44:00.609293+00:00",
      "search_url": "https://news.google.com/rss/articles/CBMiYkFVX3lxTFA2Uk9tQmFpTi15UW94UUF5aG5FOVc0b0FERlJMeGRjZU1SMlhsYmdSMFN3MXlhUTFlWTRBcnhpZUMzVWpKRnBBR0FaS0tjdG1zZnZXV2FxaGVUYWtpSXBZdUJn0gFnQVVfeXFMTlFxTjdVdE9fU29CZUdEb2ZCSzJrVzBIaGMybC1QeXVWN3pNbmVQQl95aUhCa2ZzTGRXNjJ4N2llbjJ3V3BiX3l3RGFub1BtT1BDM19QWFRjWkcwSk1NZHBxaDlieHdaUQ?oc=5",
      "source_name": "Google News - Finance",
      "source_type": "feed",
      "haiku_score": 8
    },
    {
      "id": "8a20c1dc94f6",
      "topic": "New—Fusion Help Desk for finance, sales, IT, and more - Oracle Blogs",
      "traffic": "",
      "detected_at": "2026-06-22T22:44:00.609293+00:00",
      "search_url": "https://news.google.com/rss/articles/CBMikwFBVV95cUxNOGJQWkJYOEpCLS16bGJMbDIwdE5uSHdUeGQ3NHV4UEFnblVOZF9sNzlOMDlXcGVwa1NBaFZyR0hzcEpJM2ZVaktONzlJY3lKQndvTDkwQXNQRWVpZkZhUkxiU1B3UFBleDRwYko1V0NGaWFFTUNJYW51WnVDQkxsdVBHTkxyYjVoVkZaQll5SFNQdlE?oc=5",
      "source_name": "Google News - Finance",
      "source_type": "feed",
      "haiku_score": 8
    },
    {
      "id": "b0c9f06189d8",
      "topic": "How interdepartmental connections benefit finance teams - CFO Brew",
      "traffic": "",
      "detected_at": "2026-06-22T22:44:00.609293+00:00",
      "search_url": "https://news.google.com/rss/articles/CBMimwFBVV95cUxQaDdaal9SY3NOVkRRX1hxajFFNDc1XzAyZ0FOZGFfZHRPVjdHMnlBakJ6ZUZ0REVPMjFlRlZNLWxqREZ4M2MtbjhwNHJ5VkozZHZVek93N2pZQ0VWdjY1OWhJN2FFZWgyek1IazNTTlBmN3FydFBOX1J6Mm9lRWxrWXRGYkxHZ1FJam90cUY3NUltLXZ6d3lVSFQ4Zw?oc=5",
      "source_name": "Google News - Finance",
      "source_type": "feed",
      "haiku_score": 8
    },
    {
      "id": "6648f70f8319",
      "topic": "Best Buy finance chief Matt Bilunas to step down - WTVB",
      "traffic": "",
      "detected_at": "2026-06-22T22:44:00.609293+00:00",
      "search_url": "https://news.google.com/rss/articles/CBMihgFBVV95cUxPNHFuS2NoWVBkR0k4cjJLNXVIYUY0VzJqTllIWF9yUTNmYmwtNkczYXR2bUI2U29mMFdjaUxYSkFvTC02dm9tVlJFSnVZV2I0UUJYeFFwVzE3OU5fVlNUUnFPWk5uOVFrR2hpNTd0NWF0R3QxVWR3RVU4UHJxd2xIWnlzNERYUQ?oc=5",
      "source_name": "Google News - Finance",
      "source_type": "feed",
      "haiku_score": 8
    },
    {
      "id": "ea5887901c82",
      "topic": "Time to end the SEC’s surveillance of everybody’s finances - Competitive Enterprise Institute",
      "traffic": "",
      "detected_at": "2026-06-22T22:44:00.609293+00:00",
      "search_url": "https://news.google.com/rss/articles/CBMihAFBVV95cUxONjJYQkZSWUViVWlnczZLYmdqdWxvdGZiUzJ5MHh0X2pTSHBxWF94YmJsMXluZkswcTlrVmhXdURlTjRqWExoRTFJMVZITjdfbjFyMkxIV2V6WWEtY0h1T3BJcS1ZNEJNSmJLMkp3djlCT1JGOEh3eTdrcUFlZDJsbUZSdV8?oc=5",
      "source_name": "Google News - Finance",
      "source_type": "feed",
      "haiku_score": 8
    },
    {
      "id": "0a9c152f3c7b",
      "topic": "Auto enthusiasts gather at Smokey Hollow Car Show - BrantBeacon",
      "traffic": "",
      "detected_at": "2026-06-22T22:44:00.609293+00:00",
      "search_url": "https://news.google.com/rss/articles/CBMigwFBVV95cUxQakxwVkdCVGlmSzhyaThpajlKVXV1Wmg2WlR6WldsX0xKLWttSHlRenVJU1lLek03Ym5MNmY4Ym5laEx2N1U4MU5FVHJ5LUZnMHFKbFNPX2tUZTMwLWc0VlVORUtiV2xlcEhZeHhpQjZOU2Q1R1hDQVFqejN3SkgyOHg2VQ?oc=5",
      "source_name": "Google News - Vehicles",
      "source_type": "feed",
      "haiku_score": 8
    },
    {
      "id": "47e982ca3052",
      "topic": "Super Start Extreme Car Battery Group 24F from O'Reilly Automotive Inc. - cold-cranking amps for har - AD HOC NEWS",
      "traffic": "",
      "detected_at": "2026-06-22T22:44:00.609293+00:00",
      "search_url": "https://news.google.com/rss/articles/CBMiyAFBVV95cUxObXpoeFBjM0V6X3lFVXM2cmpNckxIWEw5OVlwNVdja2JkOTFxbkVack9OYkhmcU1qZlI1cF8zTmpwQjJLeF9KRkpfWW1PQnAxQ25yOGZZZTAyd3NYY0gyTmdDNkhMdXVTR2ZxZ1lWdDJraDVUNUt0RlQzbjZMZUxEWlFRMEw1bGtMWE1jR3FsTUt3YXJXdzJObndDZjJKTVk4VklNYUNpSVh4Z0hyLWhvVmlhSWgyUnZTNWttSjd4TVJ1MnkyNktBNg?oc=5",
      "source_name": "Google News - Vehicles",
      "source_type": "feed",
      "haiku_score": 8
    },
    {
      "id": "4a97e950cdaa",
      "topic": "BMW seeks to block Zync's ITC trade secrets case despite 'mandatory laws' exception - Daily Journal",
      "traffic": "",
      "detected_at": "2026-06-22T22:44:00.609293+00:00",
      "search_url": "https://news.google.com/rss/articles/CBMiwwFBVV95cUxNdk1FdVdsallmV25RVUtDc2J1Zzhfa2M4c2Q2ZVhWMngwZjI2d055eG84VmVvSFZfZ0xXc1dVV3BHR0NIYmRtWVdSaVRjZmt2dGVtUFNzZ043Y2t6RTdVTlRTS3NWNHpIdEduS0hJd3MwYjY2QWxBeXBKN2RVdVNzdVZRYkwteEN6ZTJxYlp0clRuTGJGTFBDeWx3NUZPQmVzSnpfNWQ0U1JuTDZOMi11c0VTU1lpenNqRkRySXBLQXlnUXc?oc=5",
      "source_name": "Google News - BMW",
      "source_type": "feed",
      "haiku_score": 8
    }
  ],
  "last_checked": "2026-06-22T22:44:00.609293+00:00"
}