{
  "fetched_at": "2026-06-23T04:42:58.962075+00:00",
  "x": [
    "Randle",
    "Giannis",
    "Carl",
    "Haaland",
    "Paige",
    "Boomer Sooner",
    "Senegal",
    "Pat Riley",
    "Celtics",
    "#loveislandseason8",
    "Tucker",
    "Tino",
    "Keyon",
    "Dominguez",
    "Bonner",
    "Bottled",
    "Arias",
    "Boston",
    "Bucks",
    "Ronnie",
    "Mikey",
    "Sam Antonacci",
    "Duran",
    "Mahrez",
    "Tim Connelly",
    "Plastic",
    "Donte",
    "Sparkle",
    "Davion Mitchell",
    "Tyler Herro"
  ],
  "x_posts": [],
  "reddit_hot": [],
  "google": [],
  "youtube": [],
  "tiktok": [],
  "x_ranks": {
    "Randle": "#1",
    "Giannis": "#2",
    "Carl": "#3",
    "Haaland": "#4",
    "Paige": "#5",
    "Boomer Sooner": "#6",
    "Senegal": "#7",
    "Pat Riley": "#8",
    "Celtics": "#9",
    "#loveislandseason8": "#10",
    "Tucker": "#11",
    "Tino": "#12",
    "Keyon": "#13",
    "Dominguez": "#14",
    "Bonner": "#15",
    "Bottled": "#16",
    "Arias": "#17",
    "Boston": "#18",
    "Bucks": "#19",
    "Ronnie": "#20",
    "Mikey": "#21",
    "Sam Antonacci": "#22",
    "Duran": "#23",
    "Mahrez": "#24",
    "Tim Connelly": "#25",
    "Plastic": "#26",
    "Donte": "#27",
    "Sparkle": "#28",
    "Davion Mitchell": "#29",
    "Tyler Herro": "#30"
  },
  "google_engagement": {},
  "x_fetched_at": "",
  "google_fetched_at": ""
}