{
  "fetched_at": "2026-06-05T15:36:12.555878+00:00",
  "x": [
    "Platner",
    "Good Friday",
    "#NationalDonutDay",
    "Collins",
    "#FursuitFriday",
    "Muncy",
    "Olise",
    "#LaSayoPidiendoCacao",
    "#LastFourWatched",
    "RED Friday",
    "Happy Friyay",
    "ISAAC WOOD",
    "#FridayVibes",
    "hyuna",
    "ACC Challenge",
    "Zcash",
    "Mensik",
    "Monochromatic",
    "International Space Station",
    "Kavanaugh",
    "ASML",
    "$ZEC",
    "Lyndsey",
    "James Handy",
    "SPLC",
    "TERM LIMITS",
    "Cimo",
    "Pat White",
    "Vince Staples",
    "Shabbat Shalom"
  ],
  "x_posts": [],
  "reddit_hot": [],
  "google": [],
  "youtube": [],
  "tiktok": [],
  "x_ranks": {
    "Platner": "#1",
    "Good Friday": "#2",
    "#NationalDonutDay": "#3",
    "Collins": "#4",
    "#FursuitFriday": "#5",
    "Muncy": "#6",
    "Olise": "#7",
    "#LaSayoPidiendoCacao": "#8",
    "#LastFourWatched": "#9",
    "RED Friday": "#10",
    "Happy Friyay": "#11",
    "ISAAC WOOD": "#12",
    "#FridayVibes": "#13",
    "hyuna": "#14",
    "ACC Challenge": "#15",
    "Zcash": "#16",
    "Mensik": "#17",
    "Monochromatic": "#18",
    "International Space Station": "#19",
    "Kavanaugh": "#20",
    "ASML": "#21",
    "$ZEC": "#22",
    "Lyndsey": "#23",
    "James Handy": "#24",
    "SPLC": "#25",
    "TERM LIMITS": "#26",
    "Cimo": "#27",
    "Pat White": "#28",
    "Vince Staples": "#29",
    "Shabbat Shalom": "#30"
  },
  "google_engagement": {},
  "x_fetched_at": "",
  "google_fetched_at": ""
}