[
  {
    "timestamp": "2026-03-31T19:23:29 CT",
    "direction": "up",
    "title": "The Virgil Abloh Archive x Air Jordan 1 Headlines The April 2026 Jordan Releases Lineup",
    "source": "Sneaker News",
    "score": 8,
    "url": "https://sneakernews.com/2026/03/31/jordan-release-dates-april-2026/"
  },
  {
    "timestamp": "2026-03-31T19:24:47 CT",
    "direction": "up",
    "title": "You can finally change the goofy Gmail address you chose years ago",
    "source": "Ars Technica",
    "score": 8,
    "url": "https://arstechnica.com/gadgets/2026/03/you-can-finally-change-the-goofy-gmail-address-you-chose-years-ago/"
  },
  {
    "timestamp": "2026-03-31T19:25:15 CT",
    "direction": "down",
    "title": "Chest Hair Is Sexy Again",
    "source": "GQ",
    "score": 7,
    "url": "https://www.gq.com/story/chest-hair-is-sexy-again"
  },
  {
    "timestamp": "2026-03-31T19:25:43 CT",
    "direction": "up",
    "title": "Virgil Abloh Archive and Nike Rumored To Be Preparing Cryoshot Tiempo Release for the 2026 World Cup",
    "source": "Hypebeast",
    "score": 7,
    "url": "https://hypebeast.com/2026/3/virgil-abloh-archive-nike-cryoshot-tiempo-release-white-university-red-black-im3886-100-rumored-release"
  },
  {
    "timestamp": "2026-03-31T19:25:47 CT",
    "direction": "up",
    "title": "'Nature calls': Edwards misses tip off in return",
    "source": "ESPN",
    "score": 7,
    "url": "https://www.espn.com/nba/story/_/id/48353232/nature-calls-anthony-edwards-misses-tip-return"
  },
  {
    "timestamp": "2026-03-31T19:25:50 CT",
    "direction": "up",
    "title": "Wemby posts 3rd-fastest double-double since '97",
    "source": "ESPN",
    "score": 7,
    "url": "https://www.espn.com/nba/story/_/id/48352523/victor-wembanyama-records-fastest-double-double-history"
  },
  {
    "timestamp": "2026-03-31T19:25:53 CT",
    "direction": "up",
    "title": "Kanye West to Headline Three Nights at London's Wireless Festival 2026",
    "source": "Complex | Music, Sneakers, Pop Culture, News & Shows",
    "score": 7,
    "url": "https://www.complex.com/music/a/alex-ocho/kanye-west-wireless-festival-london-2026"
  },
  {
    "timestamp": "2026-04-01T11:26:02 CT",
    "direction": "up",
    "title": "Artemis II",
    "source": "X (Twitter) Trending",
    "score": 8,
    "url": null
  }
]
